neplocalgov/__init__.py
neplocalgov/main.py
neplocalgov-1.2.1.dist-info/LICENSE
neplocalgov-1.2.1.dist-info/METADATA
neplocalgov-1.2.1.dist-info/WHEEL
neplocalgov-1.2.1.dist-info/top_level.txt
neplocalgov-1.2.1.dist-info/RECORD
