Metadata-Version: 2.1
Name: neplocalgov
Version: 1.2.1
Summary: A python package to retreive data on Nepal local government levels.
Home-page: https://github.com/shalin-devkota/nepal-local-levels
Author: shalin-devkota
Author-email: shalin.devkota01@gmail.com
Project-URL: Bug Tracker, https://github.com/shalin-devkota/nepal-local-levels/issues
Project-URL: repository, https://github.com/shalin-devkota/nepal-local-levels
Classifier: Programming Language :: Python :: 3
Classifier: License :: OSI Approved :: MIT License
Classifier: Operating System :: OS Independent
Requires-Python: >=3.6
License-File: LICENSE
